[
  {
    "local_government_code": "23115",
    "old_postal_code": "465",
    "postal_code": "4650000",
    "prefecture_name_kana": "アイチケン",
    "city_name_kana": "ナゴヤシメイトウク",
    "town_name_kana": "イカニケイサイガナイバアイ",
    "prefecture_name": "愛知県",
    "city_name": "名古屋市名東区",
    "town_name": "以下に掲載がない場合",
    "multiple_postal_codes_per_town": "0",
    "koaza_numbering": "0",
    "has_chome": "0",
    "multiple_towns_per_postal_code": "0",
    "update_status": "0",
    "change_reason": "0"
  },
  {
    "local_government_code": "23115",
    "old_postal_code": "465",
    "postal_code": "4650016",
    "prefecture_name_kana": "アイチケン",
    "city_name_kana": "ナゴヤシメイトウク",
    "town_name_kana": "アカマツダイ",
    "prefecture_name": "愛知県",
    "city_name": "名古屋市名東区",
    "town_name": "赤松台",
    "multiple_postal_codes_per_town": "0",
    "koaza_numbering": "0",
    "has_chome": "0",
    "multiple_towns_per_postal_code": "0",
    "update_status": "0",
    "change_reason": "0"
  },
  {
    "local_government_code": "23115",
    "old_postal_code": "465",
    "postal_code": "4650033",
    "prefecture_name_kana": "アイチケン",
    "city_name_kana": "ナゴヤシメイトウク",
    "town_name_kana": "アケガオカ",
    "prefecture_name": "愛知県",
    "city_name": "名古屋市名東区",
    "town_name": "明が丘",
    "multiple_postal_codes_per_town": "0",
    "koaza_numbering": "0",
    "has_chome": "0",
    "multiple_towns_per_postal_code": "0",
    "update_status": "0",
    "change_reason": "0"
  },
  {
    "local_government_code": "23115",
    "old_postal_code": "465",
    "postal_code": "4650041",
    "prefecture_name_kana": "アイチケン",
    "city_name_kana": "ナゴヤシメイトウク",
    "town_name_kana": "アサヒガオカ",
    "prefecture_name": "愛知県",
    "city_name": "名古屋市名東区",
    "town_name": "朝日が丘",
    "multiple_postal_codes_per_town": "0",
    "koaza_numbering": "0",
    "has_chome": "0",
    "multiple_towns_per_postal_code": "0",
    "update_status": "0",
    "change_reason": "0"
  },
  {
    "local_government_code": "23115",
    "old_postal_code": "465",
    "postal_code": "4650023",
    "prefecture_name_kana": "アイチケン",
    "city_name_kana": "ナゴヤシメイトウク",
    "town_name_kana": "イシガネチョウ",
    "prefecture_name": "愛知県",
    "city_name": "名古屋市名東区",
    "town_name": "石が根町",
    "multiple_postal_codes_per_town": "0",
    "koaza_numbering": "0",
    "has_chome": "0",
    "multiple_towns_per_postal_code": "0",
    "update_status": "0",
    "change_reason": "0"
  },
  {
    "local_government_code": "23115",
    "old_postal_code": "465",
    "postal_code": "4650052",
    "prefecture_name_kana": "アイチケン",
    "city_name_kana": "ナゴヤシメイトウク",
    "town_name_kana": "イタカチョウカミヤシロ",
    "prefecture_name": "愛知県",
    "city_name": "名古屋市名東区",
    "town_name": "猪高町上社",
    "multiple_postal_codes_per_town": "0",
    "koaza_numbering": "0",
    "has_chome": "0",
    "multiple_towns_per_postal_code": "0",
    "update_status": "0",
    "change_reason": "0"
  },
  {
    "local_government_code": "23115",
    "old_postal_code": "465",
    "postal_code": "4650067",
    "prefecture_name_kana": "アイチケン",
    "city_name_kana": "ナゴヤシメイトウク",
    "town_name_kana": "イタカチョウタカバリ",
    "prefecture_name": "愛知県",
    "city_name": "名古屋市名東区",
    "town_name": "猪高町高針",
    "multiple_postal_codes_per_town": "0",
    "koaza_numbering": "0",
    "has_chome": "0",
    "multiple_towns_per_postal_code": "0",
    "update_status": "0",
    "change_reason": "0"
  },
  {
    "local_government_code": "23115",
    "old_postal_code": "465",
    "postal_code": "4650028",
    "prefecture_name_kana": "アイチケン",
    "city_name_kana": "ナゴヤシメイトウク",
    "town_name_kana": "イダカダイ",
    "prefecture_name": "愛知県",
    "city_name": "名古屋市名東区",
    "town_name": "猪高台",
    "multiple_postal_codes_per_town": "0",
    "koaza_numbering": "0",
    "has_chome": "1",
    "multiple_towns_per_postal_code": "0",
    "update_status": "0",
    "change_reason": "0"
  },
  {
    "local_government_code": "23115",
    "old_postal_code": "465",
    "postal_code": "4650093",
    "prefecture_name_kana": "アイチケン",
    "city_name_kana": "ナゴヤシメイトウク",
    "town_name_kana": "イッシャ",
    "prefecture_name": "愛知県",
    "city_name": "名古屋市名東区",
    "town_name": "一社",
    "multiple_postal_codes_per_town": "0",
    "koaza_numbering": "0",
    "has_chome": "1",
    "multiple_towns_per_postal_code": "0",
    "update_status": "0",
    "change_reason": "0"
  },
  {
    "local_government_code": "23115",
    "old_postal_code": "465",
    "postal_code": "4650021",
    "prefecture_name_kana": "アイチケン",
    "city_name_kana": "ナゴヤシメイトウク",
    "town_name_kana": "イノコイシ",
    "prefecture_name": "愛知県",
    "city_name": "名古屋市名東区",
    "town_name": "猪子石",
    "multiple_postal_codes_per_town": "0",
    "koaza_numbering": "0",
    "has_chome": "1",
    "multiple_towns_per_postal_code": "0",
    "update_status": "0",
    "change_reason": "0"
  },
  {
    "local_government_code": "23115",
    "old_postal_code": "465",
    "postal_code": "4650008",
    "prefecture_name_kana": "アイチケン",
    "city_name_kana": "ナゴヤシメイトウク",
    "town_name_kana": "イノコイシハラ",
    "prefecture_name": "愛知県",
    "city_name": "名古屋市名東区",
    "town_name": "猪子石原",
    "multiple_postal_codes_per_town": "0",
    "koaza_numbering": "0",
    "has_chome": "1",
    "multiple_towns_per_postal_code": "0",
    "update_status": "0",
    "change_reason": "0"
  },
  {
    "local_government_code": "23115",
    "old_postal_code": "465",
    "postal_code": "4650077",
    "prefecture_name_kana": "アイチケン",
    "city_name_kana": "ナゴヤシメイトウク",
    "town_name_kana": "ウエソノチョウ",
    "prefecture_name": "愛知県",
    "city_name": "名古屋市名東区",
    "town_name": "植園町",
    "multiple_postal_codes_per_town": "0",
    "koaza_numbering": "0",
    "has_chome": "1",
    "multiple_towns_per_postal_code": "0",
    "update_status": "0",
    "change_reason": "0"
  },
  {
    "local_government_code": "23115",
    "old_postal_code": "465",
    "postal_code": "4650065",
    "prefecture_name_kana": "アイチケン",
    "city_name_kana": "ナゴヤシメイトウク",
    "town_name_kana": "ウメモリザカ",
    "prefecture_name": "愛知県",
    "city_name": "名古屋市名東区",
    "town_name": "梅森坂",
    "multiple_postal_codes_per_town": "0",
    "koaza_numbering": "0",
    "has_chome": "1",
    "multiple_towns_per_postal_code": "0",
    "update_status": "0",
    "change_reason": "0"
  },
  {
    "local_government_code": "23115",
    "old_postal_code": "465",
    "postal_code": "4650066",
    "prefecture_name_kana": "アイチケン",
    "city_name_kana": "ナゴヤシメイトウク",
    "town_name_kana": "ウメモリザカニシ",
    "prefecture_name": "愛知県",
    "city_name": "名古屋市名東区",
    "town_name": "梅森坂西",
    "multiple_postal_codes_per_town": "0",
    "koaza_numbering": "0",
    "has_chome": "1",
    "multiple_towns_per_postal_code": "0",
    "update_status": "0",
    "change_reason": "0"
  },
  {
    "local_government_code": "23115",
    "old_postal_code": "465",
    "postal_code": "4650003",
    "prefecture_name_kana": "アイチケン",
    "city_name_kana": "ナゴヤシメイトウク",
    "town_name_kana": "エンジュチョウ",
    "prefecture_name": "愛知県",
    "city_name": "名古屋市名東区",
    "town_name": "延珠町",
    "multiple_postal_codes_per_town": "0",
    "koaza_numbering": "0",
    "has_chome": "0",
    "multiple_towns_per_postal_code": "0",
    "update_status": "0",
    "change_reason": "0"
  },
  {
    "local_government_code": "23115",
    "old_postal_code": "465",
    "postal_code": "4650076",
    "prefecture_name_kana": "アイチケン",
    "city_name_kana": "ナゴヤシメイトウク",
    "town_name_kana": "オウギマチ",
    "prefecture_name": "愛知県",
    "city_name": "名古屋市名東区",
    "town_name": "扇町",
    "multiple_postal_codes_per_town": "0",
    "koaza_numbering": "0",
    "has_chome": "1",
    "multiple_towns_per_postal_code": "0",
    "update_status": "0",
    "change_reason": "0"
  },
  {
    "local_government_code": "23115",
    "old_postal_code": "465",
    "postal_code": "4650064",
    "prefecture_name_kana": "アイチケン",
    "city_name_kana": "ナゴヤシメイトウク",
    "town_name_kana": "オオバリ",
    "prefecture_name": "愛知県",
    "city_name": "名古屋市名東区",
    "town_name": "大針",
    "multiple_postal_codes_per_town": "0",
    "koaza_numbering": "0",
    "has_chome": "1",
    "multiple_towns_per_postal_code": "0",
    "update_status": "0",
    "change_reason": "0"
  },
  {
    "local_government_code": "23115",
    "old_postal_code": "465",
    "postal_code": "4650005",
    "prefecture_name_kana": "アイチケン",
    "city_name_kana": "ナゴヤシメイトウク",
    "town_name_kana": "カナレ",
    "prefecture_name": "愛知県",
    "city_name": "名古屋市名東区",
    "town_name": "香流",
    "multiple_postal_codes_per_town": "0",
    "koaza_numbering": "0",
    "has_chome": "1",
    "multiple_towns_per_postal_code": "0",
    "update_status": "0",
    "change_reason": "0"
  },
  {
    "local_government_code": "23115",
    "old_postal_code": "465",
    "postal_code": "4650083",
    "prefecture_name_kana": "アイチケン",
    "city_name_kana": "ナゴヤシメイトウク",
    "town_name_kana": "カミオカチョウ",
    "prefecture_name": "愛知県",
    "city_name": "名古屋市名東区",
    "town_name": "神丘町",
    "multiple_postal_codes_per_town": "0",
    "koaza_numbering": "0",
    "has_chome": "1",
    "multiple_towns_per_postal_code": "0",
    "update_status": "0",
    "change_reason": "0"
  },
  {
    "local_government_code": "23115",
    "old_postal_code": "465",
    "postal_code": "4650082",
    "prefecture_name_kana": "アイチケン",
    "city_name_kana": "ナゴヤシメイトウク",
    "town_name_kana": "カミサト",
    "prefecture_name": "愛知県",
    "city_name": "名古屋市名東区",
    "town_name": "神里",
    "multiple_postal_codes_per_town": "0",
    "koaza_numbering": "0",
    "has_chome": "1",
    "multiple_towns_per_postal_code": "0",
    "update_status": "0",
    "change_reason": "0"
  },
  {
    "local_government_code": "23115",
    "old_postal_code": "465",
    "postal_code": "4650014",
    "prefecture_name_kana": "アイチケン",
    "city_name_kana": "ナゴヤシメイトウク",
    "town_name_kana": "カミスゲ",
    "prefecture_name": "愛知県",
    "city_name": "名古屋市名東区",
    "town_name": "上菅",
    "multiple_postal_codes_per_town": "0",
    "koaza_numbering": "0",
    "has_chome": "1",
    "multiple_towns_per_postal_code": "0",
    "update_status": "0",
    "change_reason": "0"
  },
  {
    "local_government_code": "23115",
    "old_postal_code": "465",
    "postal_code": "4650025",
    "prefecture_name_kana": "アイチケン",
    "city_name_kana": "ナゴヤシメイトウク",
    "town_name_kana": "カミヤシロ",
    "prefecture_name": "愛知県",
    "city_name": "名古屋市名東区",
    "town_name": "上社",
    "multiple_postal_codes_per_town": "0",
    "koaza_numbering": "0",
    "has_chome": "1",
    "multiple_towns_per_postal_code": "0",
    "update_status": "0",
    "change_reason": "0"
  },
  {
    "local_government_code": "23115",
    "old_postal_code": "465",
    "postal_code": "4650094",
    "prefecture_name_kana": "アイチケン",
    "city_name_kana": "ナゴヤシメイトウク",
    "town_name_kana": "カメノイ",
    "prefecture_name": "愛知県",
    "city_name": "名古屋市名東区",
    "town_name": "亀の井",
    "multiple_postal_codes_per_town": "0",
    "koaza_numbering": "0",
    "has_chome": "1",
    "multiple_towns_per_postal_code": "0",
    "update_status": "0",
    "change_reason": "0"
  },
  {
    "local_government_code": "23115",
    "old_postal_code": "465",
    "postal_code": "4650058",
    "prefecture_name_kana": "アイチケン",
    "city_name_kana": "ナゴヤシメイトウク",
    "town_name_kana": "キフネ",
    "prefecture_name": "愛知県",
    "city_name": "名古屋市名東区",
    "town_name": "貴船",
    "multiple_postal_codes_per_town": "0",
    "koaza_numbering": "0",
    "has_chome": "1",
    "multiple_towns_per_postal_code": "0",
    "update_status": "0",
    "change_reason": "0"
  },
  {
    "local_government_code": "23115",
    "old_postal_code": "465",
    "postal_code": "4650047",
    "prefecture_name_kana": "アイチケン",
    "city_name_kana": "ナゴヤシメイトウク",
    "town_name_kana": "コイケチョウ",
    "prefecture_name": "愛知県",
    "city_name": "名古屋市名東区",
    "town_name": "小池町",
    "multiple_postal_codes_per_town": "0",
    "koaza_numbering": "0",
    "has_chome": "0",
    "multiple_towns_per_postal_code": "0",
    "update_status": "0",
    "change_reason": "0"
  },
  {
    "local_government_code": "23115",
    "old_postal_code": "465",
    "postal_code": "4650044",
    "prefecture_name_kana": "アイチケン",
    "city_name_kana": "ナゴヤシメイトウク",
    "town_name_kana": "コイボリチョウ",
    "prefecture_name": "愛知県",
    "city_name": "名古屋市名東区",
    "town_name": "小井堀町",
    "multiple_postal_codes_per_town": "0",
    "koaza_numbering": "0",
    "has_chome": "0",
    "multiple_towns_per_postal_code": "0",
    "update_status": "0",
    "change_reason": "0"
  },
  {
    "local_government_code": "23115",
    "old_postal_code": "465",
    "postal_code": "4650007",
    "prefecture_name_kana": "アイチケン",
    "city_name_kana": "ナゴヤシメイトウク",
    "town_name_kana": "コウサカ",
    "prefecture_name": "愛知県",
    "city_name": "名古屋市名東区",
    "town_name": "香坂",
    "multiple_postal_codes_per_town": "0",
    "koaza_numbering": "0",
    "has_chome": "0",
    "multiple_towns_per_postal_code": "0",
    "update_status": "0",
    "change_reason": "0"
  },
  {
    "local_government_code": "23115",
    "old_postal_code": "465",
    "postal_code": "4650004",
    "prefecture_name_kana": "アイチケン",
    "city_name_kana": "ナゴヤシメイトウク",
    "town_name_kana": "コウナン",
    "prefecture_name": "愛知県",
    "city_name": "名古屋市名東区",
    "town_name": "香南",
    "multiple_postal_codes_per_town": "0",
    "koaza_numbering": "0",
    "has_chome": "1",
    "multiple_towns_per_postal_code": "0",
    "update_status": "0",
    "change_reason": "0"
  },
  {
    "local_government_code": "23115",
    "old_postal_code": "465",
    "postal_code": "4650053",
    "prefecture_name_kana": "アイチケン",
    "city_name_kana": "ナゴヤシメイトウク",
    "town_name_kana": "ゴクラク",
    "prefecture_name": "愛知県",
    "city_name": "名古屋市名東区",
    "town_name": "極楽",
    "multiple_postal_codes_per_town": "0",
    "koaza_numbering": "0",
    "has_chome": "1",
    "multiple_towns_per_postal_code": "0",
    "update_status": "0",
    "change_reason": "0"
  },
  {
    "local_government_code": "23115",
    "old_postal_code": "465",
    "postal_code": "4650096",
    "prefecture_name_kana": "アイチケン",
    "city_name_kana": "ナゴヤシメイトウク",
    "town_name_kana": "サクラガオカ",
    "prefecture_name": "愛知県",
    "city_name": "名古屋市名東区",
    "town_name": "桜が丘",
    "multiple_postal_codes_per_town": "0",
    "koaza_numbering": "0",
    "has_chome": "0",
    "multiple_towns_per_postal_code": "0",
    "update_status": "0",
    "change_reason": "0"
  },
  {
    "local_government_code": "23115",
    "old_postal_code": "465",
    "postal_code": "4650074",
    "prefecture_name_kana": "アイチケン",
    "city_name_kana": "ナゴヤシメイトウク",
    "town_name_kana": "サンコウチョウ",
    "prefecture_name": "愛知県",
    "city_name": "名古屋市名東区",
    "town_name": "山香町",
    "multiple_postal_codes_per_town": "0",
    "koaza_numbering": "0",
    "has_chome": "0",
    "multiple_towns_per_postal_code": "0",
    "update_status": "0",
    "change_reason": "0"
  },
  {
    "local_government_code": "23115",
    "old_postal_code": "465",
    "postal_code": "4650006",
    "prefecture_name_kana": "アイチケン",
    "city_name_kana": "ナゴヤシメイトウク",
    "town_name_kana": "シンゲツチョウ",
    "prefecture_name": "愛知県",
    "city_name": "名古屋市名東区",
    "town_name": "神月町",
    "multiple_postal_codes_per_town": "0",
    "koaza_numbering": "0",
    "has_chome": "0",
    "multiple_towns_per_postal_code": "0",
    "update_status": "0",
    "change_reason": "0"
  },
  {
    "local_government_code": "23115",
    "old_postal_code": "465",
    "postal_code": "4650063",
    "prefecture_name_kana": "アイチケン",
    "city_name_kana": "ナゴヤシメイトウク",
    "town_name_kana": "シンジュク",
    "prefecture_name": "愛知県",
    "city_name": "名古屋市名東区",
    "town_name": "新宿",
    "multiple_postal_codes_per_town": "0",
    "koaza_numbering": "0",
    "has_chome": "1",
    "multiple_towns_per_postal_code": "0",
    "update_status": "0",
    "change_reason": "0"
  },
  {
    "local_government_code": "23115",
    "old_postal_code": "465",
    "postal_code": "4650055",
    "prefecture_name_kana": "アイチケン",
    "city_name_kana": "ナゴヤシメイトウク",
    "town_name_kana": "セコボウ",
    "prefecture_name": "愛知県",
    "city_name": "名古屋市名東区",
    "town_name": "勢子坊",
    "multiple_postal_codes_per_town": "0",
    "koaza_numbering": "0",
    "has_chome": "1",
    "multiple_towns_per_postal_code": "0",
    "update_status": "0",
    "change_reason": "0"
  },
  {
    "local_government_code": "23115",
    "old_postal_code": "465",
    "postal_code": "4650086",
    "prefecture_name_kana": "アイチケン",
    "city_name_kana": "ナゴヤシメイトウク",
    "town_name_kana": "ダイマンチョウ",
    "prefecture_name": "愛知県",
    "city_name": "名古屋市名東区",
    "town_name": "代万町",
    "multiple_postal_codes_per_town": "0",
    "koaza_numbering": "0",
    "has_chome": "1",
    "multiple_towns_per_postal_code": "0",
    "update_status": "0",
    "change_reason": "0"
  },
  {
    "local_government_code": "23115",
    "old_postal_code": "465",
    "postal_code": "4650061",
    "prefecture_name_kana": "アイチケン",
    "city_name_kana": "ナゴヤシメイトウク",
    "town_name_kana": "タカバリ",
    "prefecture_name": "愛知県",
    "city_name": "名古屋市名東区",
    "town_name": "高針",
    "multiple_postal_codes_per_town": "0",
    "koaza_numbering": "0",
    "has_chome": "1",
    "multiple_towns_per_postal_code": "0",
    "update_status": "0",
    "change_reason": "0"
  },
  {
    "local_government_code": "23115",
    "old_postal_code": "465",
    "postal_code": "4650069",
    "prefecture_name_kana": "アイチケン",
    "city_name_kana": "ナゴヤシメイトウク",
    "town_name_kana": "タカバリアラタ",
    "prefecture_name": "愛知県",
    "city_name": "名古屋市名東区",
    "town_name": "高針荒田",
    "multiple_postal_codes_per_town": "0",
    "koaza_numbering": "0",
    "has_chome": "0",
    "multiple_towns_per_postal_code": "0",
    "update_status": "0",
    "change_reason": "0"
  },
  {
    "local_government_code": "23115",
    "old_postal_code": "465",
    "postal_code": "4650054",
    "prefecture_name_kana": "アイチケン",
    "city_name_kana": "ナゴヤシメイトウク",
    "town_name_kana": "タカバリダイ",
    "prefecture_name": "愛知県",
    "city_name": "名古屋市名東区",
    "town_name": "高針台",
    "multiple_postal_codes_per_town": "0",
    "koaza_numbering": "0",
    "has_chome": "1",
    "multiple_towns_per_postal_code": "0",
    "update_status": "0",
    "change_reason": "0"
  },
  {
    "local_government_code": "23115",
    "old_postal_code": "465",
    "postal_code": "4650073",
    "prefecture_name_kana": "アイチケン",
    "city_name_kana": "ナゴヤシメイトウク",
    "town_name_kana": "タカバリハラ",
    "prefecture_name": "愛知県",
    "city_name": "名古屋市名東区",
    "town_name": "高針原",
    "multiple_postal_codes_per_town": "0",
    "koaza_numbering": "0",
    "has_chome": "0",
    "multiple_towns_per_postal_code": "0",
    "update_status": "0",
    "change_reason": "0"
  },
  {
    "local_government_code": "23115",
    "old_postal_code": "465",
    "postal_code": "4650081",
    "prefecture_name_kana": "アイチケン",
    "city_name_kana": "ナゴヤシメイトウク",
    "town_name_kana": "タカマチョウ",
    "prefecture_name": "愛知県",
    "city_name": "名古屋市名東区",
    "town_name": "高間町",
    "multiple_postal_codes_per_town": "0",
    "koaza_numbering": "0",
    "has_chome": "0",
    "multiple_towns_per_postal_code": "0",
    "update_status": "0",
    "change_reason": "0"
  },
  {
    "local_government_code": "23115",
    "old_postal_code": "465",
    "postal_code": "4650095",
    "prefecture_name_kana": "アイチケン",
    "city_name_kana": "ナゴヤシメイトウク",
    "town_name_kana": "タカヤシロ",
    "prefecture_name": "愛知県",
    "city_name": "名古屋市名東区",
    "town_name": "高社",
    "multiple_postal_codes_per_town": "0",
    "koaza_numbering": "0",
    "has_chome": "1",
    "multiple_towns_per_postal_code": "0",
    "update_status": "0",
    "change_reason": "0"
  },
  {
    "local_government_code": "23115",
    "old_postal_code": "465",
    "postal_code": "4650034",
    "prefecture_name_kana": "アイチケン",
    "city_name_kana": "ナゴヤシメイトウク",
    "town_name_kana": "タカヤナギチョウ",
    "prefecture_name": "愛知県",
    "city_name": "名古屋市名東区",
    "town_name": "高柳町",
    "multiple_postal_codes_per_town": "0",
    "koaza_numbering": "0",
    "has_chome": "0",
    "multiple_towns_per_postal_code": "0",
    "update_status": "0",
    "change_reason": "0"
  },
  {
    "local_government_code": "23115",
    "old_postal_code": "465",
    "postal_code": "4650043",
    "prefecture_name_kana": "アイチケン",
    "city_name_kana": "ナゴヤシメイトウク",
    "town_name_kana": "タカラガオカ",
    "prefecture_name": "愛知県",
    "city_name": "名古屋市名東区",
    "town_name": "宝が丘",
    "multiple_postal_codes_per_town": "0",
    "koaza_numbering": "0",
    "has_chome": "0",
    "multiple_towns_per_postal_code": "0",
    "update_status": "0",
    "change_reason": "0"
  },
  {
    "local_government_code": "23115",
    "old_postal_code": "465",
    "postal_code": "4650027",
    "prefecture_name_kana": "アイチケン",
    "city_name_kana": "ナゴヤシメイトウク",
    "town_name_kana": "チョウダチョウ",
    "prefecture_name": "愛知県",
    "city_name": "名古屋市名東区",
    "town_name": "丁田町",
    "multiple_postal_codes_per_town": "0",
    "koaza_numbering": "0",
    "has_chome": "0",
    "multiple_towns_per_postal_code": "0",
    "update_status": "0",
    "change_reason": "0"
  },
  {
    "local_government_code": "23115",
    "old_postal_code": "465",
    "postal_code": "4650017",
    "prefecture_name_kana": "アイチケン",
    "city_name_kana": "ナゴヤシメイトウク",
    "town_name_kana": "ツツジガオカ",
    "prefecture_name": "愛知県",
    "city_name": "名古屋市名東区",
    "town_name": "つつじが丘",
    "multiple_postal_codes_per_town": "0",
    "koaza_numbering": "0",
    "has_chome": "0",
    "multiple_towns_per_postal_code": "0",
    "update_status": "0",
    "change_reason": "0"
  },
  {
    "local_government_code": "23115",
    "old_postal_code": "465",
    "postal_code": "4650042",
    "prefecture_name_kana": "アイチケン",
    "city_name_kana": "ナゴヤシメイトウク",
    "town_name_kana": "テルガオカ",
    "prefecture_name": "愛知県",
    "city_name": "名古屋市名東区",
    "town_name": "照が丘",
    "multiple_postal_codes_per_town": "0",
    "koaza_numbering": "0",
    "has_chome": "0",
    "multiple_towns_per_postal_code": "0",
    "update_status": "0",
    "change_reason": "0"
  },
  {
    "local_government_code": "23115",
    "old_postal_code": "465",
    "postal_code": "4650009",
    "prefecture_name_kana": "アイチケン",
    "city_name_kana": "ナゴヤシメイトウク",
    "town_name_kana": "テンジンシタ",
    "prefecture_name": "愛知県",
    "city_name": "名古屋市名東区",
    "town_name": "天神下",
    "multiple_postal_codes_per_town": "0",
    "koaza_numbering": "1",
    "has_chome": "0",
    "multiple_towns_per_postal_code": "0",
    "update_status": "0",
    "change_reason": "0"
  },
  {
    "local_government_code": "23115",
    "old_postal_code": "465",
    "postal_code": "4650031",
    "prefecture_name_kana": "アイチケン",
    "city_name_kana": "ナゴヤシメイトウク",
    "town_name_kana": "トミガオカ",
    "prefecture_name": "愛知県",
    "city_name": "名古屋市名東区",
    "town_name": "富が丘",
    "multiple_postal_codes_per_town": "0",
    "koaza_numbering": "0",
    "has_chome": "0",
    "multiple_towns_per_postal_code": "0",
    "update_status": "0",
    "change_reason": "0"
  },
  {
    "local_government_code": "23115",
    "old_postal_code": "465",
    "postal_code": "4650084",
    "prefecture_name_kana": "アイチケン",
    "city_name_kana": "ナゴヤシメイトウク",
    "town_name_kana": "ニシサトチョウ",
    "prefecture_name": "愛知県",
    "city_name": "名古屋市名東区",
    "town_name": "西里町",
    "multiple_postal_codes_per_town": "0",
    "koaza_numbering": "0",
    "has_chome": "1",
    "multiple_towns_per_postal_code": "0",
    "update_status": "0",
    "change_reason": "0"
  },
  {
    "local_government_code": "23115",
    "old_postal_code": "465",
    "postal_code": "4650071",
    "prefecture_name_kana": "アイチケン",
    "city_name_kana": "ナゴヤシメイトウク",
    "town_name_kana": "ニシヤマダイ",
    "prefecture_name": "愛知県",
    "city_name": "名古屋市名東区",
    "town_name": "西山台",
    "multiple_postal_codes_per_town": "0",
    "koaza_numbering": "0",
    "has_chome": "0",
    "multiple_towns_per_postal_code": "0",
    "update_status": "0",
    "change_reason": "0"
  },
  {
    "local_government_code": "23115",
    "old_postal_code": "465",
    "postal_code": "4650085",
    "prefecture_name_kana": "アイチケン",
    "city_name_kana": "ナゴヤシメイトウク",
    "town_name_kana": "ニシヤマホントオリ",
    "prefecture_name": "愛知県",
    "city_name": "名古屋市名東区",
    "town_name": "西山本通",
    "multiple_postal_codes_per_town": "0",
    "koaza_numbering": "0",
    "has_chome": "1",
    "multiple_towns_per_postal_code": "0",
    "update_status": "0",
    "change_reason": "0"
  },
  {
    "local_government_code": "23115",
    "old_postal_code": "465",
    "postal_code": "4650078",
    "prefecture_name_kana": "アイチケン",
    "city_name_kana": "ナゴヤシメイトウク",
    "town_name_kana": "ニジガオカ",
    "prefecture_name": "愛知県",
    "city_name": "名古屋市名東区",
    "town_name": "にじが丘",
    "multiple_postal_codes_per_town": "0",
    "koaza_numbering": "0",
    "has_chome": "1",
    "multiple_towns_per_postal_code": "0",
    "update_status": "0",
    "change_reason": "0"
  },
  {
    "local_government_code": "23115",
    "old_postal_code": "465",
    "postal_code": "4650046",
    "prefecture_name_kana": "アイチケン",
    "city_name_kana": "ナゴヤシメイトウク",
    "town_name_kana": "ノゾミガオカ",
    "prefecture_name": "愛知県",
    "city_name": "名古屋市名東区",
    "town_name": "望が丘",
    "multiple_postal_codes_per_town": "0",
    "koaza_numbering": "0",
    "has_chome": "0",
    "multiple_towns_per_postal_code": "0",
    "update_status": "0",
    "change_reason": "0"
  },
  {
    "local_government_code": "23115",
    "old_postal_code": "465",
    "postal_code": "4650056",
    "prefecture_name_kana": "アイチケン",
    "city_name_kana": "ナゴヤシメイトウク",
    "town_name_kana": "ノマチョウ",
    "prefecture_name": "愛知県",
    "city_name": "名古屋市名東区",
    "town_name": "野間町",
    "multiple_postal_codes_per_town": "0",
    "koaza_numbering": "0",
    "has_chome": "0",
    "multiple_towns_per_postal_code": "0",
    "update_status": "0",
    "change_reason": "0"
  },
  {
    "local_government_code": "23115",
    "old_postal_code": "465",
    "postal_code": "4650018",
    "prefecture_name_kana": "アイチケン",
    "city_name_kana": "ナゴヤシメイトウク",
    "town_name_kana": "ハチマエ",
    "prefecture_name": "愛知県",
    "city_name": "名古屋市名東区",
    "town_name": "八前",
    "multiple_postal_codes_per_town": "0",
    "koaza_numbering": "0",
    "has_chome": "1",
    "multiple_towns_per_postal_code": "0",
    "update_status": "0",
    "change_reason": "0"
  },
  {
    "local_government_code": "23115",
    "old_postal_code": "465",
    "postal_code": "4650002",
    "prefecture_name_kana": "アイチケン",
    "city_name_kana": "ナゴヤシメイトウク",
    "town_name_kana": "ヒキヤマ",
    "prefecture_name": "愛知県",
    "city_name": "名古屋市名東区",
    "town_name": "引山",
    "multiple_postal_codes_per_town": "0",
    "koaza_numbering": "0",
    "has_chome": "1",
    "multiple_towns_per_postal_code": "0",
    "update_status": "0",
    "change_reason": "0"
  },
  {
    "local_government_code": "23115",
    "old_postal_code": "465",
    "postal_code": "4650045",
    "prefecture_name_kana": "アイチケン",
    "city_name_kana": "ナゴヤシメイトウク",
    "town_name_kana": "ヒメワカチョウ",
    "prefecture_name": "愛知県",
    "city_name": "名古屋市名東区",
    "town_name": "姫若町",
    "multiple_postal_codes_per_town": "0",
    "koaza_numbering": "0",
    "has_chome": "0",
    "multiple_towns_per_postal_code": "0",
    "update_status": "0",
    "change_reason": "0"
  },
  {
    "local_government_code": "23115",
    "old_postal_code": "465",
    "postal_code": "4650037",
    "prefecture_name_kana": "アイチケン",
    "city_name_kana": "ナゴヤシメイトウク",
    "town_name_kana": "フジカチョウ",
    "prefecture_name": "愛知県",
    "city_name": "名古屋市名東区",
    "town_name": "藤香町",
    "multiple_postal_codes_per_town": "0",
    "koaza_numbering": "0",
    "has_chome": "0",
    "multiple_towns_per_postal_code": "0",
    "update_status": "0",
    "change_reason": "0"
  },
  {
    "local_government_code": "23115",
    "old_postal_code": "465",
    "postal_code": "4650032",
    "prefecture_name_kana": "アイチケン",
    "city_name_kana": "ナゴヤシメイトウク",
    "town_name_kana": "フジガオカ",
    "prefecture_name": "愛知県",
    "city_name": "名古屋市名東区",
    "town_name": "藤が丘",
    "multiple_postal_codes_per_town": "0",
    "koaza_numbering": "0",
    "has_chome": "0",
    "multiple_towns_per_postal_code": "0",
    "update_status": "0",
    "change_reason": "0"
  },
  {
    "local_government_code": "23115",
    "old_postal_code": "465",
    "postal_code": "4650036",
    "prefecture_name_kana": "アイチケン",
    "city_name_kana": "ナゴヤシメイトウク",
    "town_name_kana": "フジサトチョウ",
    "prefecture_name": "愛知県",
    "city_name": "名古屋市名東区",
    "town_name": "藤里町",
    "multiple_postal_codes_per_town": "0",
    "koaza_numbering": "0",
    "has_chome": "0",
    "multiple_towns_per_postal_code": "0",
    "update_status": "0",
    "change_reason": "0"
  },
  {
    "local_government_code": "23115",
    "old_postal_code": "465",
    "postal_code": "4650075",
    "prefecture_name_kana": "アイチケン",
    "city_name_kana": "ナゴヤシメイトウク",
    "town_name_kana": "フジマキチョウ",
    "prefecture_name": "愛知県",
    "city_name": "名古屋市名東区",
    "town_name": "藤巻町",
    "multiple_postal_codes_per_town": "0",
    "koaza_numbering": "0",
    "has_chome": "1",
    "multiple_towns_per_postal_code": "0",
    "update_status": "0",
    "change_reason": "0"
  },
  {
    "local_government_code": "23115",
    "old_postal_code": "465",
    "postal_code": "4650048",
    "prefecture_name_kana": "アイチケン",
    "city_name_kana": "ナゴヤシメイトウク",
    "town_name_kana": "フジミガオカ",
    "prefecture_name": "愛知県",
    "city_name": "名古屋市名東区",
    "town_name": "藤見が丘",
    "multiple_postal_codes_per_town": "0",
    "koaza_numbering": "0",
    "has_chome": "0",
    "multiple_towns_per_postal_code": "0",
    "update_status": "0",
    "change_reason": "0"
  },
  {
    "local_government_code": "23115",
    "old_postal_code": "465",
    "postal_code": "4650026",
    "prefecture_name_kana": "アイチケン",
    "city_name_kana": "ナゴヤシメイトウク",
    "town_name_kana": "フジモリ",
    "prefecture_name": "愛知県",
    "city_name": "名古屋市名東区",
    "town_name": "藤森",
    "multiple_postal_codes_per_town": "0",
    "koaza_numbering": "0",
    "has_chome": "1",
    "multiple_towns_per_postal_code": "0",
    "update_status": "0",
    "change_reason": "0"
  },
  {
    "local_government_code": "23115",
    "old_postal_code": "465",
    "postal_code": "4650022",
    "prefecture_name_kana": "アイチケン",
    "city_name_kana": "ナゴヤシメイトウク",
    "town_name_kana": "フジモリニシマチ",
    "prefecture_name": "愛知県",
    "city_name": "名古屋市名東区",
    "town_name": "藤森西町",
    "multiple_postal_codes_per_town": "0",
    "koaza_numbering": "0",
    "has_chome": "0",
    "multiple_towns_per_postal_code": "0",
    "update_status": "0",
    "change_reason": "0"
  },
  {
    "local_government_code": "23115",
    "old_postal_code": "465",
    "postal_code": "4650012",
    "prefecture_name_kana": "アイチケン",
    "city_name_kana": "ナゴヤシメイトウク",
    "town_name_kana": "ブンキョウダイ",
    "prefecture_name": "愛知県",
    "city_name": "名古屋市名東区",
    "town_name": "文教台",
    "multiple_postal_codes_per_town": "0",
    "koaza_numbering": "0",
    "has_chome": "1",
    "multiple_towns_per_postal_code": "0",
    "update_status": "0",
    "change_reason": "0"
  },
  {
    "local_government_code": "23115",
    "old_postal_code": "465",
    "postal_code": "4650097",
    "prefecture_name_kana": "アイチケン",
    "city_name_kana": "ナゴヤシメイトウク",
    "town_name_kana": "ヘイワガオカ",
    "prefecture_name": "愛知県",
    "city_name": "名古屋市名東区",
    "town_name": "平和が丘",
    "multiple_postal_codes_per_town": "0",
    "koaza_numbering": "0",
    "has_chome": "1",
    "multiple_towns_per_postal_code": "0",
    "update_status": "0",
    "change_reason": "0"
  },
  {
    "local_government_code": "23115",
    "old_postal_code": "465",
    "postal_code": "4650024",
    "prefecture_name_kana": "アイチケン",
    "city_name_kana": "ナゴヤシメイトウク",
    "town_name_kana": "ホンゴウ",
    "prefecture_name": "愛知県",
    "city_name": "名古屋市名東区",
    "town_name": "本郷",
    "multiple_postal_codes_per_town": "0",
    "koaza_numbering": "0",
    "has_chome": "1",
    "multiple_towns_per_postal_code": "0",
    "update_status": "0",
    "change_reason": "0"
  },
  {
    "local_government_code": "23115",
    "old_postal_code": "465",
    "postal_code": "4650068",
    "prefecture_name_kana": "アイチケン",
    "city_name_kana": "ナゴヤシメイトウク",
    "town_name_kana": "マキノサト",
    "prefecture_name": "愛知県",
    "city_name": "名古屋市名東区",
    "town_name": "牧の里",
    "multiple_postal_codes_per_town": "0",
    "koaza_numbering": "0",
    "has_chome": "1",
    "multiple_towns_per_postal_code": "0",
    "update_status": "0",
    "change_reason": "0"
  },
  {
    "local_government_code": "23115",
    "old_postal_code": "465",
    "postal_code": "4650072",
    "prefecture_name_kana": "アイチケン",
    "city_name_kana": "ナゴヤシメイトウク",
    "town_name_kana": "マキノハラ",
    "prefecture_name": "愛知県",
    "city_name": "名古屋市名東区",
    "town_name": "牧の原",
    "multiple_postal_codes_per_town": "0",
    "koaza_numbering": "0",
    "has_chome": "1",
    "multiple_towns_per_postal_code": "0",
    "update_status": "0",
    "change_reason": "0"
  },
  {
    "local_government_code": "23115",
    "old_postal_code": "465",
    "postal_code": "4650062",
    "prefecture_name_kana": "アイチケン",
    "city_name_kana": "ナゴヤシメイトウク",
    "town_name_kana": "マツイチョウ",
    "prefecture_name": "愛知県",
    "city_name": "名古屋市名東区",
    "town_name": "松井町",
    "multiple_postal_codes_per_town": "0",
    "koaza_numbering": "0",
    "has_chome": "0",
    "multiple_towns_per_postal_code": "0",
    "update_status": "0",
    "change_reason": "0"
  },
  {
    "local_government_code": "23115",
    "old_postal_code": "465",
    "postal_code": "4650087",
    "prefecture_name_kana": "アイチケン",
    "city_name_kana": "ナゴヤシメイトウク",
    "town_name_kana": "メイトウホンドオリ",
    "prefecture_name": "愛知県",
    "city_name": "名古屋市名東区",
    "town_name": "名東本通",
    "multiple_postal_codes_per_town": "0",
    "koaza_numbering": "0",
    "has_chome": "1",
    "multiple_towns_per_postal_code": "0",
    "update_status": "0",
    "change_reason": "0"
  },
  {
    "local_government_code": "23115",
    "old_postal_code": "465",
    "postal_code": "4650088",
    "prefecture_name_kana": "アイチケン",
    "city_name_kana": "ナゴヤシメイトウク",
    "town_name_kana": "メイトウホンマチ",
    "prefecture_name": "愛知県",
    "city_name": "名古屋市名東区",
    "town_name": "名東本町",
    "multiple_postal_codes_per_town": "0",
    "koaza_numbering": "0",
    "has_chome": "0",
    "multiple_towns_per_postal_code": "0",
    "update_status": "0",
    "change_reason": "0"
  },
  {
    "local_government_code": "23115",
    "old_postal_code": "465",
    "postal_code": "4650051",
    "prefecture_name_kana": "アイチケン",
    "city_name_kana": "ナゴヤシメイトウク",
    "town_name_kana": "ヤシロガオカ",
    "prefecture_name": "愛知県",
    "city_name": "名古屋市名東区",
    "town_name": "社が丘",
    "multiple_postal_codes_per_town": "0",
    "koaza_numbering": "0",
    "has_chome": "1",
    "multiple_towns_per_postal_code": "0",
    "update_status": "0",
    "change_reason": "0"
  },
  {
    "local_government_code": "23115",
    "old_postal_code": "465",
    "postal_code": "4650013",
    "prefecture_name_kana": "アイチケン",
    "city_name_kana": "ナゴヤシメイトウク",
    "town_name_kana": "ヤシログチ",
    "prefecture_name": "愛知県",
    "city_name": "名古屋市名東区",
    "town_name": "社口",
    "multiple_postal_codes_per_town": "0",
    "koaza_numbering": "0",
    "has_chome": "1",
    "multiple_towns_per_postal_code": "0",
    "update_status": "0",
    "change_reason": "0"
  },
  {
    "local_government_code": "23115",
    "old_postal_code": "465",
    "postal_code": "4650092",
    "prefecture_name_kana": "アイチケン",
    "city_name_kana": "ナゴヤシメイトウク",
    "town_name_kana": "ヤシロダイ",
    "prefecture_name": "愛知県",
    "city_name": "名古屋市名東区",
    "town_name": "社台",
    "multiple_postal_codes_per_town": "0",
    "koaza_numbering": "0",
    "has_chome": "1",
    "multiple_towns_per_postal_code": "0",
    "update_status": "0",
    "change_reason": "0"
  },
  {
    "local_government_code": "23115",
    "old_postal_code": "465",
    "postal_code": "4650011",
    "prefecture_name_kana": "アイチケン",
    "city_name_kana": "ナゴヤシメイトウク",
    "town_name_kana": "ヤマノテ",
    "prefecture_name": "愛知県",
    "city_name": "名古屋市名東区",
    "town_name": "山の手",
    "multiple_postal_codes_per_town": "0",
    "koaza_numbering": "0",
    "has_chome": "1",
    "multiple_towns_per_postal_code": "0",
    "update_status": "0",
    "change_reason": "0"
  },
  {
    "local_government_code": "23115",
    "old_postal_code": "465",
    "postal_code": "4650035",
    "prefecture_name_kana": "アイチケン",
    "city_name_kana": "ナゴヤシメイトウク",
    "town_name_kana": "ユタカガオカ",
    "prefecture_name": "愛知県",
    "city_name": "名古屋市名東区",
    "town_name": "豊が丘",
    "multiple_postal_codes_per_town": "0",
    "koaza_numbering": "0",
    "has_chome": "0",
    "multiple_towns_per_postal_code": "0",
    "update_status": "0",
    "change_reason": "0"
  },
  {
    "local_government_code": "23115",
    "old_postal_code": "465",
    "postal_code": "4650091",
    "prefecture_name_kana": "アイチケン",
    "city_name_kana": "ナゴヤシメイトウク",
    "town_name_kana": "ヨモギダイ",
    "prefecture_name": "愛知県",
    "city_name": "名古屋市名東区",
    "town_name": "よもぎ台",
    "multiple_postal_codes_per_town": "0",
    "koaza_numbering": "0",
    "has_chome": "1",
    "multiple_towns_per_postal_code": "0",
    "update_status": "0",
    "change_reason": "0"
  },
  {
    "local_government_code": "23115",
    "old_postal_code": "465",
    "postal_code": "4650057",
    "prefecture_name_kana": "アイチケン",
    "city_name_kana": "ナゴヤシメイトウク",
    "town_name_kana": "リクマエチョウ",
    "prefecture_name": "愛知県",
    "city_name": "名古屋市名東区",
    "town_name": "陸前町",
    "multiple_postal_codes_per_town": "0",
    "koaza_numbering": "0",
    "has_chome": "0",
    "multiple_towns_per_postal_code": "0",
    "update_status": "0",
    "change_reason": "0"
  },
  {
    "local_government_code": "23115",
    "old_postal_code": "465",
    "postal_code": "4650015",
    "prefecture_name_kana": "アイチケン",
    "city_name_kana": "ナゴヤシメイトウク",
    "town_name_kana": "ワカバダイ",
    "prefecture_name": "愛知県",
    "city_name": "名古屋市名東区",
    "town_name": "若葉台",
    "multiple_postal_codes_per_town": "0",
    "koaza_numbering": "0",
    "has_chome": "0",
    "multiple_towns_per_postal_code": "0",
    "update_status": "0",
    "change_reason": "0"
  }
]