[
  {
    "local_government_code": "35207",
    "old_postal_code": "744",
    "postal_code": "7440061",
    "prefecture_name_kana": "ヤマグチケン",
    "city_name_kana": "クダマツシ",
    "town_name_kana": "コウチ",
    "prefecture_name": "山口県",
    "city_name": "下松市",
    "town_name": "河内",
    "multiple_postal_codes_per_town": "0",
    "koaza_numbering": "0",
    "has_chome": "0",
    "multiple_towns_per_postal_code": "1",
    "update_status": "0",
    "change_reason": "0"
  },
  {
    "local_government_code": "35207",
    "old_postal_code": "744",
    "postal_code": "7440061",
    "prefecture_name_kana": "ヤマグチケン",
    "city_name_kana": "クダマツシ",
    "town_name_kana": "コウチ（アオバダイ）",
    "prefecture_name": "山口県",
    "city_name": "下松市",
    "town_name": "河内（青葉台）",
    "multiple_postal_codes_per_town": "1",
    "koaza_numbering": "0",
    "has_chome": "0",
    "multiple_towns_per_postal_code": "1",
    "update_status": "0",
    "change_reason": "0"
  },
  {
    "local_government_code": "35207",
    "old_postal_code": "744",
    "postal_code": "7440061",
    "prefecture_name_kana": "ヤマグチケン",
    "city_name_kana": "クダマツシ",
    "town_name_kana": "コウチ（オオコウチ）",
    "prefecture_name": "山口県",
    "city_name": "下松市",
    "town_name": "河内（大河内）",
    "multiple_postal_codes_per_town": "1",
    "koaza_numbering": "0",
    "has_chome": "0",
    "multiple_towns_per_postal_code": "1",
    "update_status": "0",
    "change_reason": "0"
  },
  {
    "local_government_code": "35207",
    "old_postal_code": "744",
    "postal_code": "7440061",
    "prefecture_name_kana": "ヤマグチケン",
    "city_name_kana": "クダマツシ",
    "town_name_kana": "コウチ（オカイチ）",
    "prefecture_name": "山口県",
    "city_name": "下松市",
    "town_name": "河内（岡市）",
    "multiple_postal_codes_per_town": "1",
    "koaza_numbering": "0",
    "has_chome": "0",
    "multiple_towns_per_postal_code": "1",
    "update_status": "0",
    "change_reason": "0"
  },
  {
    "local_government_code": "35207",
    "old_postal_code": "744",
    "postal_code": "7440061",
    "prefecture_name_kana": "ヤマグチケン",
    "city_name_kana": "クダマツシ",
    "town_name_kana": "コウチ（オカノハラチョウ）",
    "prefecture_name": "山口県",
    "city_name": "下松市",
    "town_name": "河内（岡ノ原町）",
    "multiple_postal_codes_per_town": "1",
    "koaza_numbering": "0",
    "has_chome": "0",
    "multiple_towns_per_postal_code": "1",
    "update_status": "0",
    "change_reason": "0"
  },
  {
    "local_government_code": "35207",
    "old_postal_code": "744",
    "postal_code": "7440061",
    "prefecture_name_kana": "ヤマグチケン",
    "city_name_kana": "クダマツシ",
    "town_name_kana": "コウチ（カワセ）",
    "prefecture_name": "山口県",
    "city_name": "下松市",
    "town_name": "河内（川瀬）",
    "multiple_postal_codes_per_town": "1",
    "koaza_numbering": "0",
    "has_chome": "0",
    "multiple_towns_per_postal_code": "1",
    "update_status": "0",
    "change_reason": "0"
  },
  {
    "local_government_code": "35207",
    "old_postal_code": "744",
    "postal_code": "7440061",
    "prefecture_name_kana": "ヤマグチケン",
    "city_name_kana": "クダマツシ",
    "town_name_kana": "コウチ（クダマツセントシティ）",
    "prefecture_name": "山口県",
    "city_name": "下松市",
    "town_name": "河内（下松セントシティ）",
    "multiple_postal_codes_per_town": "1",
    "koaza_numbering": "0",
    "has_chome": "0",
    "multiple_towns_per_postal_code": "1",
    "update_status": "0",
    "change_reason": "0"
  },
  {
    "local_government_code": "35207",
    "old_postal_code": "744",
    "postal_code": "7440061",
    "prefecture_name_kana": "ヤマグチケン",
    "city_name_kana": "クダマツシ",
    "town_name_kana": "コウチ（クボ）",
    "prefecture_name": "山口県",
    "city_name": "下松市",
    "town_name": "河内（久保）",
    "multiple_postal_codes_per_town": "1",
    "koaza_numbering": "0",
    "has_chome": "0",
    "multiple_towns_per_postal_code": "1",
    "update_status": "0",
    "change_reason": "0"
  },
  {
    "local_government_code": "35207",
    "old_postal_code": "744",
    "postal_code": "7440061",
    "prefecture_name_kana": "ヤマグチケン",
    "city_name_kana": "クダマツシ",
    "town_name_kana": "コウチ（クボイチ）",
    "prefecture_name": "山口県",
    "city_name": "下松市",
    "town_name": "河内（久保市）",
    "multiple_postal_codes_per_town": "1",
    "koaza_numbering": "0",
    "has_chome": "0",
    "multiple_towns_per_postal_code": "1",
    "update_status": "0",
    "change_reason": "0"
  },
  {
    "local_government_code": "35207",
    "old_postal_code": "744",
    "postal_code": "7440061",
    "prefecture_name_kana": "ヤマグチケン",
    "city_name_kana": "クダマツシ",
    "town_name_kana": "コウチ（クロクイ）",
    "prefecture_name": "山口県",
    "city_name": "下松市",
    "town_name": "河内（黒杭）",
    "multiple_postal_codes_per_town": "1",
    "koaza_numbering": "0",
    "has_chome": "0",
    "multiple_towns_per_postal_code": "1",
    "update_status": "0",
    "change_reason": "0"
  },
  {
    "local_government_code": "35207",
    "old_postal_code": "744",
    "postal_code": "7440061",
    "prefecture_name_kana": "ヤマグチケン",
    "city_name_kana": "クダマツシ",
    "town_name_kana": "コウチ（コノ）",
    "prefecture_name": "山口県",
    "city_name": "下松市",
    "town_name": "河内（小野）",
    "multiple_postal_codes_per_town": "1",
    "koaza_numbering": "0",
    "has_chome": "0",
    "multiple_towns_per_postal_code": "1",
    "update_status": "0",
    "change_reason": "0"
  },
  {
    "local_government_code": "35207",
    "old_postal_code": "744",
    "postal_code": "7440061",
    "prefecture_name_kana": "ヤマグチケン",
    "city_name_kana": "クダマツシ",
    "town_name_kana": "コウチ（サチガオカ）",
    "prefecture_name": "山口県",
    "city_name": "下松市",
    "town_name": "河内（幸ケ丘）",
    "multiple_postal_codes_per_town": "1",
    "koaza_numbering": "0",
    "has_chome": "0",
    "multiple_towns_per_postal_code": "1",
    "update_status": "0",
    "change_reason": "0"
  },
  {
    "local_government_code": "35207",
    "old_postal_code": "744",
    "postal_code": "7440061",
    "prefecture_name_kana": "ヤマグチケン",
    "city_name_kana": "クダマツシ",
    "town_name_kana": "コウチ（ショウワドオリ）",
    "prefecture_name": "山口県",
    "city_name": "下松市",
    "town_name": "河内（昭和通り）",
    "multiple_postal_codes_per_town": "1",
    "koaza_numbering": "0",
    "has_chome": "0",
    "multiple_towns_per_postal_code": "1",
    "update_status": "0",
    "change_reason": "0"
  },
  {
    "local_government_code": "35207",
    "old_postal_code": "744",
    "postal_code": "7440061",
    "prefecture_name_kana": "ヤマグチケン",
    "city_name_kana": "クダマツシ",
    "town_name_kana": "コウチ（ジョウヤマダイ）",
    "prefecture_name": "山口県",
    "city_name": "下松市",
    "town_name": "河内（城山台）",
    "multiple_postal_codes_per_town": "1",
    "koaza_numbering": "0",
    "has_chome": "0",
    "multiple_towns_per_postal_code": "1",
    "update_status": "0",
    "change_reason": "0"
  },
  {
    "local_government_code": "35207",
    "old_postal_code": "744",
    "postal_code": "7440061",
    "prefecture_name_kana": "ヤマグチケン",
    "city_name_kana": "クダマツシ",
    "town_name_kana": "コウチ（スドオリ）",
    "prefecture_name": "山口県",
    "city_name": "下松市",
    "town_name": "河内（素通り）",
    "multiple_postal_codes_per_town": "1",
    "koaza_numbering": "0",
    "has_chome": "0",
    "multiple_towns_per_postal_code": "1",
    "update_status": "0",
    "change_reason": "0"
  },
  {
    "local_government_code": "35207",
    "old_postal_code": "744",
    "postal_code": "7440061",
    "prefecture_name_kana": "ヤマグチケン",
    "city_name_kana": "クダマツシ",
    "town_name_kana": "コウチ（タニ）",
    "prefecture_name": "山口県",
    "city_name": "下松市",
    "town_name": "河内（谷）",
    "multiple_postal_codes_per_town": "1",
    "koaza_numbering": "0",
    "has_chome": "0",
    "multiple_towns_per_postal_code": "1",
    "update_status": "0",
    "change_reason": "0"
  },
  {
    "local_government_code": "35207",
    "old_postal_code": "744",
    "postal_code": "7440061",
    "prefecture_name_kana": "ヤマグチケン",
    "city_name_kana": "クダマツシ",
    "town_name_kana": "コウチ（ツツジガオカ）",
    "prefecture_name": "山口県",
    "city_name": "下松市",
    "town_name": "河内（つつじケ丘）",
    "multiple_postal_codes_per_town": "1",
    "koaza_numbering": "0",
    "has_chome": "0",
    "multiple_towns_per_postal_code": "1",
    "update_status": "0",
    "change_reason": "0"
  },
  {
    "local_government_code": "35207",
    "old_postal_code": "744",
    "postal_code": "7440061",
    "prefecture_name_kana": "ヤマグチケン",
    "city_name_kana": "クダマツシ",
    "town_name_kana": "コウチ（デアイ）",
    "prefecture_name": "山口県",
    "city_name": "下松市",
    "town_name": "河内（出合）",
    "multiple_postal_codes_per_town": "1",
    "koaza_numbering": "0",
    "has_chome": "0",
    "multiple_towns_per_postal_code": "1",
    "update_status": "0",
    "change_reason": "0"
  },
  {
    "local_government_code": "35207",
    "old_postal_code": "744",
    "postal_code": "7440061",
    "prefecture_name_kana": "ヤマグチケン",
    "city_name_kana": "クダマツシ",
    "town_name_kana": "コウチ（トノガエキ）",
    "prefecture_name": "山口県",
    "city_name": "下松市",
    "town_name": "河内（殿ケ浴）",
    "multiple_postal_codes_per_town": "1",
    "koaza_numbering": "0",
    "has_chome": "0",
    "multiple_towns_per_postal_code": "1",
    "update_status": "0",
    "change_reason": "0"
  },
  {
    "local_government_code": "35207",
    "old_postal_code": "744",
    "postal_code": "7440061",
    "prefecture_name_kana": "ヤマグチケン",
    "city_name_kana": "クダマツシ",
    "town_name_kana": "コウチ（ナカトハラ）",
    "prefecture_name": "山口県",
    "city_name": "下松市",
    "town_name": "河内（中戸原）",
    "multiple_postal_codes_per_town": "1",
    "koaza_numbering": "0",
    "has_chome": "0",
    "multiple_towns_per_postal_code": "1",
    "update_status": "0",
    "change_reason": "0"
  },
  {
    "local_government_code": "35207",
    "old_postal_code": "744",
    "postal_code": "7440061",
    "prefecture_name_kana": "ヤマグチケン",
    "city_name_kana": "クダマツシ",
    "town_name_kana": "コウチ（ナルカワ）",
    "prefecture_name": "山口県",
    "city_name": "下松市",
    "town_name": "河内（成川）",
    "multiple_postal_codes_per_town": "1",
    "koaza_numbering": "0",
    "has_chome": "0",
    "multiple_towns_per_postal_code": "1",
    "update_status": "0",
    "change_reason": "0"
  },
  {
    "local_government_code": "35207",
    "old_postal_code": "744",
    "postal_code": "7440061",
    "prefecture_name_kana": "ヤマグチケン",
    "city_name_kana": "クダマツシ",
    "town_name_kana": "コウチ（ニノセ）",
    "prefecture_name": "山口県",
    "city_name": "下松市",
    "town_name": "河内（二ノ瀬）",
    "multiple_postal_codes_per_town": "1",
    "koaza_numbering": "0",
    "has_chome": "0",
    "multiple_towns_per_postal_code": "1",
    "update_status": "0",
    "change_reason": "0"
  },
  {
    "local_government_code": "35207",
    "old_postal_code": "744",
    "postal_code": "7440061",
    "prefecture_name_kana": "ヤマグチケン",
    "city_name_kana": "クダマツシ",
    "town_name_kana": "コウチ（ヒノデチョウ）",
    "prefecture_name": "山口県",
    "city_name": "下松市",
    "town_name": "河内（日ノ出町）",
    "multiple_postal_codes_per_town": "1",
    "koaza_numbering": "0",
    "has_chome": "0",
    "multiple_towns_per_postal_code": "1",
    "update_status": "0",
    "change_reason": "0"
  },
  {
    "local_government_code": "35207",
    "old_postal_code": "744",
    "postal_code": "7440061",
    "prefecture_name_kana": "ヤマグチケン",
    "city_name_kana": "クダマツシ",
    "town_name_kana": "コウチ（ヨシワラ）",
    "prefecture_name": "山口県",
    "city_name": "下松市",
    "town_name": "河内（吉原）",
    "multiple_postal_codes_per_town": "1",
    "koaza_numbering": "0",
    "has_chome": "0",
    "multiple_towns_per_postal_code": "1",
    "update_status": "0",
    "change_reason": "0"
  }
]